hpractice/__init__.py
hpractice/main.py
hpractice-0.0.3.dist-info/LICENSE
hpractice-0.0.3.dist-info/METADATA
hpractice-0.0.3.dist-info/WHEEL
hpractice-0.0.3.dist-info/top_level.txt
hpractice-0.0.3.dist-info/RECORD
