Metadata-Version: 2.1
Name: hpractice
Version: 0.0.3
Summary: My package for practicing to deploy on PyPI.
Author-email: llHoYall <hoya@example.com>
Classifier: Programming Language :: Python :: 3
Classifier: License :: OSI Approved :: MIT License
Classifier: Operating System :: OS Independent
Requires-Python: >=3.8
License-File: LICENSE
